{
  "id_query": "17687631",
  "total": 19622,
  "total_current": 200,
  "max_score": 60.662113,
  "origin_question": "Cho hỏi bản 32gb này nếu mua mới thì được cài sẵn iOS mấy vậy QTV, ios 8, 9 hay 10",
  "hits": [
    {
      "score": 60.662113,
      "id": "17687631",
      "field_search": "question",
      "question": "Cho hỏi bản 32gb này nếu mua mới thì được cài sẵn iOS mấy vậy QTV, ios 8, 9 hay 10",
      "answer": "Chào bạn, Khi mua sản phẩm này, máy sẽ được cài sẵn iOS 10 bạn nha! Nếu bạn quan tâm, bạn có thể để lại số điện thoại để bên em hỗ trợ bạn đặt hàng ạ! Mong phản hồi từ bạn!",
      "relate_q_q": 3
    },
    {
      "score": 36.660393,
      "id": "22434516",
      "field_search": "question",
      "question": "Iphone 6 bản 32gb đc cài sẵn ios mấy vậy qtv",
      "answer": "Chào bạn.Dạ trường hợp này thì còn tùy vào từng đợt hàng sản xuất nên bên mình cũng không kiểm tra được bạn nhé. Tùy vào lô hàng nhập về mà Apple cài ios mấy cho máy đó ạ có thể là ios 10 cũng có thể là ios 11 nha bạn. Thông tin đến bạn.",
      "relate_q_q": 2
    },
    {
      "score": 36.059666,
      "id": "19452540",
      "field_search": "question",
      "question": "ip6 32gb được cài sẵn ios 10 chấm mấy vậy ạ",
      "answer": "Chào bạn,Dạ còn tùy lô hàng bạn nhé, bạn vui lòng ra tận siêu thị bên mình nơi có hàng để được hỗ trợ tốt nhất bạn nhaThân gửi đến bạn.",
      "relate_q_q": 2
    },
    {
      "score": 32.211884,
      "id": "19405709",
      "field_search": "question",
      "question": "lúc mới mua máy cài sẵn ios 10 phiên bản nào ạ",
      "answer": "Chào bạn, Theo mình thấy thì trường hợp này tùy theo lô hàng, iPhone 6 32GB hiện tại khi xuất xưởng đã được hỗ trợ cập nhật IOS 10 trở lên  nha bạn, Thân chào bạn !",
      "relate_q_q": 2
    },
    {
      "score": 29.70885,
      "id": "19620401",
      "field_search": "question",
      "question": "Cho hỏi máy dc cài sẵn ios mấy vậy shop?",
      "answer": "Chào anh,Dạ với sản phẩm trên thì khi mua tại Thegioididong.com thì sẽ được cài sẵn IOS 10 anh nhé.Thông tin đến anh!",
      "relate_q_q": 2
    },
    {
      "score": 29.610981,
      "id": "17445286",
      "field_search": "question",
      "question": "Cho hỏi máy này ios 9 hay 10",
      "answer": "Chào bạn,Trường hợp này thì máy chạy IOS 10 bạn nha, bạn cần tìm hiểu thêm thông tin nào khác về sản phẩm vui lòng phản hồi tại đây để bên mình có thể hỗ trợ nha. Thông tin đến bạn, thân chào bạn !",
      "relate_q_q": 2
    },
    {
      "score": 28.08466,
      "id": "21646099",
      "field_search": "question",
      "question": "Iphone 6 32ghb này lúc mới mua là phiên bản ios 10 hay 10.3.2 vậy Qtv",
      "answer": "Chào anh,Hiện máy này đang ở phiên bản iOS 10 anh nhé.Thông tin đến anh.",
      "relate_q_q": 2
    },
    {
      "score": 27.790333,
      "id": "24115272",
      "field_search": "question",
      "question": "Máy mới hiện nay cài sẵn hệ điều hành IOS mấy vậy ad?",
      "answer": "Chào bạn,Dạ do sẽ tùy lô hàng khác nhau mà máy sẽ chạy phiên bản hệ điều hành khác nhau, nếu bạn mua máy là lô hàng mới thì có thể sẽ là phiên bản iOS 11 bạn nha.Xin thông tin đến bạn!",
      "relate_q_q": 2
    },
    {
      "score": 27.700668,
      "id": "26525798",
      "field_search": "question",
      "question": "Ad cho hỏi ip 6 32G fuxbox thì đag chạy ios 8, 9 hay 10.ạ",
      "answer": "Chào bạn,Dạ ở đây còn tùy thời gian kích hoạt máy nữa bạn nhé; nhưng đa số mình thấy là các máy khi kích hoạt mới hiện tại phần nhiều là IOS 11 rồi ạ.Chia sẻ cùng bạn!",
      "relate_q_q": 2
    },
    {
      "score": 27.305176,
      "id": "26441131",
      "field_search": "question",
      "question": "Máy đang bán tại cửa hàng được cài sẵn iOS mấy vậy ạ",
      "answer": "Chào anh !  Hiện thì bản IOS là bản IOS 11 anh nhé. Nếu được anh vui lòng cho em xin thông tin khu vực ( đường,quận, huyện) anh cần mua hàng để bên em kiểm tra giúp anh siêu thị khu vực của anh có hàng không anh nha. Mong phản hồi từ anh.",
      "relate_q_q": 2
    },
    {
      "score": 26.301416,
      "id": "27525180",
      "field_search": "question",
      "question": "Mình vừa mới mua bản này, nhưng không hiểu sao máy lại cài sẵn ios 11. Nên máy giật lag có chút thất vọng. Mình cứ nghĩ là máy này cũ chạy sẵn ios 10 thôi.",
      "answer": "Chào anh,Tuỳ vào lô hàng mà apple sẽ cập nhật sản phẩm đó lên bản cao nhất, em thấy iphone 6 dùng ios 11 cũng khá là mượt nên anh có thể yên tâm sử dụng sản phẩm và apple sẽ thường xuyên cập nhật để máy của anh hoạt động tốt hơn và bảo mật hơn nha.Thông tin đến anh.",
      "relate_q_q": 1
    },
    {
      "score": 25.884016,
      "id": "20219107",
      "field_search": "question",
      "question": "Iphone 6 32gb mới tại tgdđ chạy sẵn ios mấy ?",
      "answer": "Chào anh Phi,Sản phẩm Iphone 6 32GB bên em kinh doanh khi mới mua sẽ chạy sẵn hệ điều hành IOS 10 đó ạ. Anh có thể về cập nhật bản mới nhất anh nhé.Thông tin đến anh.",
      "relate_q_q": 2
    },
    {
      "score": 24.824894,
      "id": "23280407",
      "field_search": "question",
      "question": "Cho mình hỏi máy mình mới mua hôm qua đc cài sẵn ios 11.0.3 bây giờ có bản cập nhật mới ios 11.1.2 có nên Lên ko",
      "answer": "Chào bạnTrường hợp này nếu máy bạn đang sử dụng ổn định thì bạn khoan hãy cập nhật máy lên phiên bản mới , bạn chờ thêm 1 khoảng thời gian nữa rồi hãy cập nhật để phần mềm được hoàn hỉnh hơn bạn nha .Thông tin đến bạn .",
      "relate_q_q": -1
    },
    {
      "score": 24.618557,
      "id": "23464387",
      "field_search": "question",
      "question": "ad cho hỏi là nếu lên ios 11.1.2 thì bây giờ còn xuống được phiên bản ios 10 k ạ?",
      "answer": "Chào bạn.Dạ với iPhone 6 thì rất tiếc Apple đã khóa ios 10 lại rồi không còn hạ cấp được nữa bạn nhé. Thông tin đến bạn.",
      "relate_q_q": -1
    },
    {
      "score": 24.233803,
      "id": "31153386",
      "field_search": "question",
      "question": "QTV TGDĐ cho mình hỏi iPhone 6 32GB này giờ Active thì máy ở IOS mấy vậy ?",
      "answer": "Chào anh , Dạ điện thoại này anh mua bên em là chạy hệ điều hành iOS 11 trở lên cả rồi anh nhé. Thông tin đến anh .",
      "relate_q_q": -1
    },
    {
      "score": 24.056372,
      "id": "18082471",
      "field_search": "question",
      "question": "Xin QTV iPhone 6 32gb mua mới khui hộp đã chạy sẵn IOS mấy rồi ạ? Xin cảm ơn.",
      "answer": "Chào anh,Đối với sản phẩm này, bên em đang kinh doanh tại siêu thị Thegioididong.com với hệ điều hành iOS 10 nha anh. Nếu anh quan tâm đến sản phẩm này, anh vui lòng để lại thông tin khu vực anh đang ở để em có thể hỗ trợ kiểm tra hàng giúp anh, anh nhé.Thông tin đến anh!",
      "relate_q_q": -1
    },
    {
      "score": 23.96141,
      "id": "17436844",
      "field_search": "question",
      "question": "Anh/chị ơi máy này khi xuất xưởng đã cài sẵn ios 10 rồi ạ",
      "answer": "Chào anh,Hiện tại thì sản phẩm iPhone 6 32Gb sắp về, bên em chưa kinh doanh nên chưa có thông tin cụ thể anh nhé.Thân gửi anh !",
      "relate_q_q": 1
    },
    {
      "score": 23.84139,
      "id": "20556577",
      "field_search": "question",
      "question": "Iphone 632gb 2017 chạy ios 9 hay 10 vậy ạ",
      "answer": "Chào anh,Điện thoại iPhone 6 32GB hiện bên em sử dụng IOS 10 anh nhé.Thân gửi thông tin đến anh!",
      "relate_q_q": 2
    },
    {
      "score": 23.340607,
      "id": "24328335",
      "field_search": "question",
      "question": "Mấy anh cho e hỏi cái ạ...  Iphone 6 có ios 10 không hay là đã cài lên ios 11 hết rồi ạ...???",
      "answer": "Chào anh Bảo,Dạ với trường hợp này thì còn tùy lô nữa nha anh. Có thể là IOS 10 hoặc IOS 11 anh nhé. Nếu anh quan tâm đến sản phẩm này, anh vui lòng phản hồi thông tin khu vực anh đang ở tại ô bình luận, bên em sẽ hỗ trợ kiểm tra hàng giúp anh.Mong phản hồi từ anh!",
      "relate_q_q": 1
    },
    {
      "score": 23.149803,
      "id": "26270366",
      "field_search": "question",
      "question": "mua mới mình muốn bên hãng cài lại ios 10 thì có được không. mong QTV trl giúp mình. cảm ơn",
      "answer": "Chào anh !Hiện nay Apple đã khóa sign các phiên bản iOS 10 rồi nha anh nên anh mang máy đến hãng cũng không được hỗ trợ cài nha anh.Thông tin đến anh.",
      "relate_q_q": 1
    },
    {
      "score": 23.01139,
      "id": "18249507",
      "field_search": "question",
      "question": "con này đang ở ios 10. mấy vậy.",
      "answer": "Chào anh Hiện máy của bên em đang kinh doanh đang chạy Hệ điều hành IOS 10 anh nhé. Nếu anh chỉ sử dụng các tính năng cơ bản thông thường thì sản phẩm này có thể khá là bền và ổn định đó ạ. Tuy nhiên, tùy theo sự phát triển của công nghệ mà có thể ra các sản phẩm mới tốt hơn tân tiến hơn hoặc các ứng dụng ngày càng nặng hơn do cập nhật nhiều tính năng thêm cho người dùng dẫn tới bộ nhớ trong không đủ lưu trữ anh nhé.Xin gửi thông tin đến anh ",
      "relate_q_q": 1
    },
    {
      "score": 22.870523,
      "id": "24558115",
      "field_search": "question",
      "question": "cho em hỏi cái này chạy ios 10 hay 11 vậy ad",
      "answer": "Chào bạn, Trường hợp này thì sẽ tùy vào từng đợt nhập hàng mà sẽ được nhà sản xuất hỗ trợ cập nhật các phiên bản khác nhau và là máy nguyên Seal nên mình không kiểm tra cho bạn được mong bạn thông cảm nhé.Xin thông tin đến bạn ạ !",
      "relate_q_q": 2
    },
    {
      "score": 22.719862,
      "id": "24557974",
      "field_search": "question",
      "question": "cho em hỏi cái này chạy ios 10 hay 11 vậy ad",
      "answer": "Chào bạn.Dạ trường hợp này thì bên mình không thể kiểm tra chính xác được bạn nhé. Vì tùy vào từng lô hàng đợt hàng về từ Apple sẽ có máy là ios 10, có máy là ios 11 đó ạ. Thông tin đến bạn.",
      "relate_q_q": 2
    },
    {
      "score": 22.327406,
      "id": "28335698",
      "field_search": "question",
      "question": "Nếu cài bản Ios 12 beta thì khi có ios12 chính thức thì có cần gỡ bản này không ạ?",
      "answer": "Chào bạn,Cần bạn nha, bạn cần trở về bản IOS 11.4 sau đó cập nhật lên IOS 12 chính thức bạn nhé.Thông tin đến bạn !",
      "relate_q_q": -1
    },
    {
      "score": 22.300533,
      "id": "22405274",
      "field_search": "question",
      "question": "Ios 10 chấm mấy vậy!?",
      "answer": "Chào bạn, iPhone 6 tùy vào từng đợt nhập hàng mà đã được nhà sản xuất hỗ trợ cập nhật các phiên bản hệ điều hành khác nhau nên mình không thể kiểm tra cho bạn được mong bạn thông cảm nhé.Thân chào bạn !",
      "relate_q_q": 1
    },
    {
      "score": 22.257862,
      "id": "21525543",
      "field_search": "question",
      "question": "cho e hỏi có thể xuống ios 9 được k ạ.. ios 10 hao pin qa ạ",
      "answer": "Chào bạn.Dạ rất tiếc thì khi đã nâng cấp thì không hỗ trợ hạ cấp được nữa bạn nhé.Thông tin đến bạn.",
      "relate_q_q": -1
    },
    {
      "score": 22.091343,
      "id": "24864749",
      "field_search": "question",
      "question": "khi mua máy mới thì ios nó là ios mấy vậy ạ",
      "answer": "Chào chị,Hiện tại khi chị mua máy mới, máy chạy  iOS 10 chị nhéThân gửi đến chị.",
      "relate_q_q": 2
    },
    {
      "score": 22.085596,
      "id": "19949428",
      "field_search": "question",
      "question": "Cho mình hỏi IOS 10 cụ thể là 10. mấy vậy? cảm ơn",
      "answer": "Chào bạn Trường hợp này sẽ tùy thuộc lô hàng nhưng đa phần máy sẽ được cập nhật lên iOS mới nhất là 10.3.2 bạn nhé .Thông tin đến bạn .",
      "relate_q_q": 1
    },
    {
      "score": 22.082535,
      "id": "24984885",
      "field_search": "question",
      "question": "Máy cài sẵn ios 11 à",
      "answer": "Chào anh Hiện khi chưa mở máy thì máy sẽ là IOS 10 anh nhé. Còn sau khi mở máy lên sẽ cập nhật chạy lên điều hành cao nhất cho máy anh nhé.Xin gửi thông tin đến anh.",
      "relate_q_q": 1
    },
    {
      "score": 21.852133,
      "id": "24727080",
      "field_search": "question",
      "question": "cái này chạy ios 10 hay 11 vậy",
      "answer": "Chào anh,Tuỳ vào sản phẩm thì máy sẽ chạy ios 10 hay 11 ạ, nhưng anh yên tâm với sản phẩm trên thì 10 hay 11 đều tốt nên anh chọn mua sản phẩm thoải mái nha.Thông tin đến anh.",
      "relate_q_q": 2
    },
    {
      "score": 21.757875,
      "id": "25390030",
      "field_search": "question",
      "question": "Iphone 6 được cài hệ điều hành ios mấy vậy ạ",
      "answer": "Chào bạn,Mình kiểm tra các máy Iphone 6 mới khi active là ios 11 bạn nhé.Thông tin đến bạn.",
      "relate_q_q": 2
    },
    {
      "score": 21.563599,
      "id": "22479043",
      "field_search": "question",
      "question": "Mk dùng IOS 10, cho mk hỏi làm sao để ios 11 k tự động tải xuống...nó cứ tải sẵn rồi chờ mk cài @@",
      "answer": "Chào bạn.Trường hợp này bạn thử giúp mình vào cài đặt > cài đặt chung > dung lượng > bạn chọn ứng dụng IOS 11 > xóa cài đặt giúp mình bạn nhé.Thông tin đến bạn.",
      "relate_q_q": -1
    },
    {
      "score": 21.437832,
      "id": "26835628",
      "field_search": "question",
      "question": "Bây giờ mua máy thì khi active máy. Máy sẽ chạy IOS Máy ạ. Ios 8 hoặc 9 được ko ạ",
      "answer": "Chào bạn, Điện thoại này giờ bạn mua bên mình là lô hàng mới sẽ chạy hệ điều hành iOS 11 bạn nhé. thông tin đến bạn .",
      "relate_q_q": 1
    },
    {
      "score": 21.059034,
      "id": "26461442",
      "field_search": "question",
      "question": "Iphone 6 32gb này còn bản ios 10 ko ạ hạy toàn đã lên ios 11 rồi ad ?",
      "answer": "Chào bạn, xin lỗi đã để bạn đợi lâu nhé Theo mình thấy thì với các lô hàng mới, hãng đã cập nhật cho máy lên ios 11 bạn nhé Thân chào bạn!",
      "relate_q_q": 2
    },
    {
      "score": 20.996689,
      "id": "18322443",
      "field_search": "question",
      "question": "Iphone nay hê diêu hanh ios 10 hay mua vê mới nâng câp lên ios 10",
      "answer": "Chào anh Hiện sản phẩm này đã được cài đặt sẵn Hệ điều hành IOS 10 rồi anh nhé. Nếu anh có thắc mắc gì thêm, xin để lại lời nhắn để bên em có thể hỗ trợ thêm ạ. Xin gửi thông tin đến anh",
      "relate_q_q": 1
    },
    {
      "score": 20.95952,
      "id": "27730453",
      "field_search": "question",
      "question": "cho em hỏi máy iphone chạy IOS  mấy mới hoạt động mượt mà ios 11.3 hay 11.4 hay 12.0",
      "answer": "Chào bạn,Dạ hiện nay phiên bản mượt nhất trong 3 phiên bản bạn nêu là IOS 12 bạn nhé.Xin thông tin đến bạn.",
      "relate_q_q": -1
    },
    {
      "score": 20.822514,
      "id": "23602813",
      "field_search": "question",
      "question": "mới mua về máy này dùng ios mấy ?",
      "answer": "Chào anh Hiện sản phẩm mới đập hộp chạy IOS 10 anh nhé. Tuy nhiên, khi anh mở máy thì máy sẽ tự động cập nhật lên phiên bản IOS mới nhất hiện hành anh nhé.Xin gửi thông tin đến anh.",
      "relate_q_q": 2
    },
    {
      "score": 20.815235,
      "id": "25807047",
      "field_search": "question",
      "question": "Cho mình hỏi là thế giới di động có bán IOS phiên bản 9 ko ạ.mình đang cần máy IOS phiên bản 9",
      "answer": "Chào anh, Dạ hiện tại bên em chỉ đang có sản phẩm phiên bản IOS 11 trở lên thôi anh nhé.Thông tin đến anh.",
      "relate_q_q": -1
    },
    {
      "score": 20.720346,
      "id": "23987191",
      "field_search": "question",
      "question": "HĐH mới nhất hiện tại là IOS mấy vậy QTV",
      "answer": "Chào bạn,Phiên bản iOS chính thức mới nhất hiện tại là iOS 11.2.1 bạn nhé. Thân chào bạn !",
      "relate_q_q": -1
    },
    {
      "score": 20.629158,
      "id": "24537848",
      "field_search": "question",
      "question": "ad cho mình hỏi ip6 32gb chạy ios 10 hay 11 v ạ?",
      "answer": "Chào bạn, Trường hợp này thì sẽ tùy vào từng đợt nhập hàng mà sẽ được nhà sản xuất hỗ trợ cập nhật các phiên bản hệ điều hành IOS khác nhau và bản mới nhất mà máy được hỗ trợ là IOS iOS 11.2.2 nha bạn.Xin thông tin đến bạn ạ !",
      "relate_q_q": 2
    },
    {
      "score": 20.565916,
      "id": "17515347",
      "field_search": "question",
      "question": "cho mình hỏi ,HDH IOS 09 và IOS 10 có khác nhau nhiều ko?mình thấy bên ngoài add ghi IOS 9.chi tiết ghi IOS 10?",
      "answer": "Chào anh,Dạ iOS 10 là  bản nâng cấp nhiều của iOS 9 với nhiều tính năng hay ạ, anh vui lòng tham khảo chi tiết  nhé.Xin được thông tin đến anh !",
      "relate_q_q": -1
    },
    {
      "score": 20.480612,
      "id": "25985980",
      "field_search": "question",
      "question": "Mình mua về là ios 11 giờ có thể mang qua tgdd up lại bản ios 10 được không vậy",
      "answer": "Chào bạn, xin lỗi đã để bạn đợi lâu nhé Rất tiếc là hãng chỉ hỗ trợ người dùng nâng cấp hệ điều hành lên, chứ không hỗ trợ hạ xuống bạn nhé. Mong bạn thông cảm nha  Thân chào bạn!",
      "relate_q_q": -1
    },
    {
      "score": 20.428154,
      "id": "18136327",
      "field_search": "question",
      "question": "Ủa em tưởng hồi mới ra mắt ip 6 chạy ios 8 hay 9 mà anh/chị ơi",
      "answer": "Chào anh, Trường hợp này đối với sản phẩm iPhone 6 32GB khi mới ra mắt đã được hỗ trợ sử dụng hệ điệu hành IOS 10 rồi anh nhé. Thông tin đến anh!",
      "relate_q_q": 1
    },
    {
      "score": 20.41381,
      "id": "25931371",
      "field_search": "question",
      "question": "máy này chạy ios11 có giật lag ko? nếu mình mua máy mới muốn xài ios 10 được không ad?",
      "answer": "Chào bạn,Dạ sản phẩm này chạy IOS 11 tốt lắm nhé, khá mượt mà đó bạn, tuy nhiên còn việc sử dụng iOS 10 thì không được do sản phẩm này mặc định hiện tại là iOS 11 rồi ạThân gửi đến bạn.",
      "relate_q_q": -1
    },
    {
      "score": 20.204641,
      "id": "20778727",
      "field_search": "question",
      "question": "QTV ơi cho hỏi tại sao mình k cài đặt ios 10.3.3 được",
      "answer": "Chào bạn, Trường hợp này có thể là do kết nối mạng của điện thoại bạn không được tốt .Bạn kết nối mạng Wifi khác mạnh và ổn định hơn rồi thử lại nhé . Mong phản hồi từ bạn  !",
      "relate_q_q": -1
    },
    {
      "score": 20.200054,
      "id": "19452195",
      "field_search": "question",
      "question": "Lúc mới mua ip6duoc cai săn ios 10 chấm mấy j a",
      "answer": "Chào bạn, Theo mình thấy thì trường hợp này tùy theo lô hàng, iPhone 6 32GB hiện tại khi xuất xưởng đã được hỗ trợ cập nhật IOS 10 trở lên nha bạn, Thân chào bạn !",
      "relate_q_q": 2
    },
    {
      "score": 20.102911,
      "id": "20134667",
      "field_search": "question",
      "question": "sao trên này gì là hệ điều hành ios 10  mà ở ngoài thực tế là ios 9 vậy a",
      "answer": "Chào bạn Trường hợp này sẽ tùy thuộc lô hàng bạn nhé , bạn vẫn có thể cập nhật máy lên iOS 10.3.2 mới nhất bình thường ạ .Thông tin đến bạn .",
      "relate_q_q": 1
    },
    {
      "score": 20.059233,
      "id": "19264893",
      "field_search": "question",
      "question": "Iphone 6 này còn phiên bản màu khác trên toàn hệ thống không ạ? Với lại là khi mua về là máy chạy sẵn ios 10 hay sao. Cảm ơn!",
      "answer": "Chào anh Khánh,Rất tiếc là với sản phẩm trên thì bên em chỉ có màu vàng đồng thôi anh nha. Và với sản phẩm trên thì khi mua về đã được tích hợp sẵn IOS 10 anh nhé.Thông tin đến anh!",
      "relate_q_q": -1
    },
    {
      "score": 20.016098,
      "id": "28550050",
      "field_search": "question",
      "question": "Ad cho hỏi iPhone 6 bản 16g thì ios 11.4.1 và ios 11.2.6 bản nào mượt hơn vậy",
      "answer": "Chào bạn Theo trải nghiệm cá nhân của mình thì phiên bản iOS 11.4.1 sử dụng mượt mà hơn bạn nhé .Thông tin đến bạn .",
      "relate_q_q": -1
    },
    {
      "score": 19.902279,
      "id": "19407704",
      "field_search": "question",
      "question": "Máy mới mua về là được cài sẵn icloud hay sao qtv và mình ko sử dụng icloud được ko,qtv chỉ cho e kiểm tra icloud ở đâu",
      "answer": "Chào bạn,Máy mới mua không được cài sẵn iCloud , máy không dùng iCloud cũng được nhé bạn .Bạn vào cài đặt > iCloud > tại đây bạn sẽ thấy tài khoản iCloud của máy được đăng nhập nếu có nhé. Thân chào bạn !",
      "relate_q_q": -1
    },
    {
      "score": 19.823372,
      "id": "24843454",
      "field_search": "question",
      "question": "Em mua mấy iphone 6 ios 11 cảm thấy ức chế về cái hệ điều hành ios 11 hay lỗi . Liệu em có được đổi máy khác ios 10 được không",
      "answer": "Thân chào anh,Nếu sản phẩm có lỗi do nhà sản xuất anh sẽ được 1 đổi 1 trong vòng 1 tháng anh nhé, còn nếu không ưng ý anh có thể bán lại cho siêu thị Thegioididong.com và mua sản phẩm khác anh nha, Nếu sản phẩm được mua mới ở Thegioididong, còn trong thời gian bảo hành, không bị hư hỏng trầy xước, siêu thị sẽ thu mua lại giúp mình ạ, . Bên em có chính sách là tháng đầu tiên mất 20% giá trị sản phẩm và tháng tiếp theo giảm thêm 5% nữa ạ.Thân gửi anh!",
      "relate_q_q": -1
    },
    {
      "score": 19.784086,
      "id": "25190276",
      "field_search": "question",
      "question": "Cho mình hỏi con Iphone 6 này là bản IOS 11 chính thức hay bản beta ?",
      "answer": "Chào bạn,Dạ nếu bạn đề cập máy mới, vừa kích hoạt luôn thì là bản IOS 11 chính thức bạn nhé--- nhưng phần chi tiết là bản 11.x.x bao nhiêu thì còn tùy thời điểm kích hoạt nữa bạn nha, mình rất tiếc là chưa có thông số cụ thể cho bạn rồi ạ.Chia sẻ cùng bạn!",
      "relate_q_q": 1
    },
    {
      "score": 19.777134,
      "id": "21668447",
      "field_search": "question",
      "question": "Iphone 6 là bản ios mấy vậy ad",
      "answer": "Chào anh,Hiện tại do bên em không mở máy được nên em không dám chắc phiên bản ios của máy nhưng em đoán là từ ios 9 đến ios 10 nha.Thông tin đến anh.",
      "relate_q_q": 2
    },
    {
      "score": 19.712618,
      "id": "25117331",
      "field_search": "question",
      "question": "Mình mới mua vài ngày . Máy cài sẵng ios 11 nên k dc mượt . Giờ mình muốn hạ xuống ios 8 thì phải làm sao ạ",
      "answer": "Chào bạn, Rất tiếc, hiện tại Apple đã khóa nên không thể quay về phiên bản cũ được nha bạn nên khi sử dụng game thì trước khi vào game bạn tắt các ứng dụng chạy ngầm, giảm cấu hình game về mức thấp hơn (nếu game hỗ trợ) và nếu là game Online thì kết nối với mạng wifi ổn định xem sao nha bạn.Xin thông tin đến bạn ạ !",
      "relate_q_q": -1
    },
    {
      "score": 19.705166,
      "id": "17686652",
      "field_search": "question",
      "question": "máy này chạy ios mấy vậy",
      "answer": "Chào anh, Sản phẩm này được chạy trên phiên bản iOS 10 anh nhé. Thông tin đến anh!",
      "relate_q_q": 2
    },
    {
      "score": 19.63882,
      "id": "21287094",
      "field_search": "question",
      "question": "Ad ơi em mới mua iphone 6 32gb máy hệ điêug hành ios 10 nếu muốn nâng lên 10.3.3 thì sao anh",
      "answer": "Chào bạn,Dạ bạn có thể kiểm tra bằng cách vào cài đặt- cài đặt chung- cập nhật phần mềm- bạn bật mạng và chờ hệ thống phản hồi nâng cấp là được bạn nhé.Chia sẻ cùng bạn!",
      "relate_q_q": -1
    },
    {
      "score": 19.618929,
      "id": "19165517",
      "field_search": "question",
      "question": "Em ơi máy này ios được mấy năm nữa vậy em?",
      "answer": "Chào chị Thảo,Em chưa hiểu ios được bao nhiêu lâu nữa là sao vậy chị, chị có thể nói cụ thể hơn để em hỗ trợ chị nha! Và với 2 thông tin còn lại về giá máy có giảm nữa không, máy bán lâu nữa thì em không có thông tin để hỗ trợ chị được, rất mong chị thông cảm nha! Các thông tin này điều là của hãng hết chị nhé!Xin thông tin đến chị!",
      "relate_q_q": -1
    },
    {
      "score": 19.60545,
      "id": "31329156",
      "field_search": "question",
      "question": "Ad cho e hỏi . hiện tại e xai dk 4 năm đang để pb ios 8 . vậy nay e updel thì sẽ lên ios mấy ạ",
      "answer": "Chào bạn,Dạ hiện khi bạn update máy sẽ lên thẳng bản IOS 12.1 bạn nhé.Thân chào bạn.",
      "relate_q_q": -1
    },
    {
      "score": 19.600471,
      "id": "23407339",
      "field_search": "question",
      "question": "máy này chạy ios mấy vậy",
      "answer": "Chào anh, Điện thoại iPhone 6 32GB hỗ trợ hệ điều hành  iOS 10 anh nha. Hiện bên em có hỗ trợ giá rẻ online cho sản phẩm, anh có thể đặt hàng tại web để mua với giá ưu đãi anh nhé.Thông tin đến anh.",
      "relate_q_q": 2
    },
    {
      "score": 19.598465,
      "id": "31852919",
      "field_search": "question",
      "question": "Máy này khi mua về lên ios mấy vậy",
      "answer": "Chào chị Dạ trường hợp này còn tùy vào từng lô hàng ạ, phiên bản cao nhất hiện tại là Ios 12.1.2 chị nhé. Thông tin đến chị.",
      "relate_q_q": 2
    },
    {
      "score": 19.541607,
      "id": "26394678",
      "field_search": "question",
      "question": "cho em hỏi khi mua IP6 này khi active nó sẽ tự động lên IOS mới nhất hay là chạy IOS 8 ban đầu của nó ạ. Em tính mua nhưng sợ lên IOS 11 may chậm",
      "answer": "Chào bạn,Với các lô hàng mới thì máy sẽ được cài sẵn iOS 11 nha bạn. Vói iPhone 6 khi cập nhật iOS 11.3 thì máy vẫn hoạt động ổn định và mượt mà bạn nha. Nên bạn có thể an tâm về hiệu năng máy nhé.Thân chào bạn !",
      "relate_q_q": 1
    },
    {
      "score": 19.427744,
      "id": "24055764",
      "field_search": "question",
      "question": "Cho minh hỏi iPhone 6 32 GB còn ios 10 kg vậy qtv",
      "answer": "Chào anh! Dạ. Về trường hợp của anh, thì tùy lô anh nha. Có lô thì hệ điều hành IOS 10. Hoặc IOS 11 anh nha. Nên bên em không thể có thông tin chính xác được ạ. Anh vui lòng ra siêu thị  Thegioididong.com gần nhất để nhân viên bên em phục vụ mình tốt nhất ạ. Chân thành cảm ơn anh!",
      "relate_q_q": -1
    },
    {
      "score": 19.387758,
      "id": "24925011",
      "field_search": "question",
      "question": "Ad cho mình hỏi iphone 6 32gb này ios 10 có đúng không ạ",
      "answer": "Chào chị,Dạ các sản phẩm iPhone 6 32GB ở siêu thị bên em chạy iOS 10 đó chị nhé, tuy nhiên tùy theo lô hàng chị nha, ở 1 số sản phẩm cũng có các bản cao hơn tuy nhiên đa số là iOS 10 nhaChia sẻ cùng chị.",
      "relate_q_q": 1
    },
    {
      "score": 19.318672,
      "id": "22079780",
      "field_search": "question",
      "question": "Cho mình hỏi máy này là bản lock hay nguyên bản vậy qtv",
      "answer": "Chào bạn,iPhone 6 này là phiên bản quốc tế bạn nhé. Thân chào bạn !",
      "relate_q_q": -1
    },
    {
      "score": 19.248047,
      "id": "21087845",
      "field_search": "question",
      "question": "Mình muốn ip 6 32gb bản ios thấp hơn ios 10 hiện tại, có k bạn?",
      "answer": "Chào anh,Dạ hiện tại bên em chỉ kinh doanh sản phẩm iphone 6 32GB phiên bản IOS 10 thôi anh ạ, nếu anh quan tâm vui lòng để lại số điện thoại bên em sẽ hỗ trợ anh đặt hàng nhé.Mong phản hồi từ anh!",
      "relate_q_q": -1
    },
    {
      "score": 19.23812,
      "id": "22785834",
      "field_search": "question",
      "question": "cho mình hỏi ip6 mới khui hợp ra thì chạy ios 10.?.? ạ",
      "answer": "Chào anh, Với sản phẩm này bên em kinh doanh nguyên seal và đã cài đặt sẳn IOS 10 anh nhé . Thông tin đến anh.",
      "relate_q_q": 1
    },
    {
      "score": 19.221146,
      "id": "24684793",
      "field_search": "question",
      "question": "cho e hỏi mua máy ip6 32G này mặc định nó là ios 10 ko a, hay là ios 11 khi mua máy tại thời điểm này ạ",
      "answer": "Chào bạn,Trường hợp này thì còn tùy vào máy bạn mua thuộc lô hàng nào bạn nha, nếu lô hàng mới thì sẽ là bản IOS mới bạn nhé.Thông tin đến bạn !",
      "relate_q_q": 2
    },
    {
      "score": 19.208502,
      "id": "20722884",
      "field_search": "question",
      "question": "khi lên ios 11beta 4 thì nếu có bản chính thức thì phải hạ cấp mới cập nhật được sao ?",
      "answer": "Chào bạn, Khi có bản chính thức thì bạn vẫn cập nhật trực tiếp được nha.Xin thông tin đến bạn.",
      "relate_q_q": -1
    },
    {
      "score": 19.187534,
      "id": "27668218",
      "field_search": "question",
      "question": "Đây là bản ios 11 do nhà sản xuất cho  luôn hay là từ bản ios 10 của máy nâg cấp lên ios11 ạ",
      "answer": "Chào anh Hiện đây là bản IOS 11 được nhà sản xuất nâng cấp trong đợt sản xuất đó luôn anh nhé. Hiện sản phẩm bên em kinh doanh nguyên seal nên không thể tự động nâng cấp được ạ.Xin gửi thông tin đến anh.",
      "relate_q_q": 1
    },
    {
      "score": 19.142126,
      "id": "27096595",
      "field_search": "question",
      "question": "Cho em hỏi mình nên để hđh ios 10 hay nâng lên ios 11",
      "answer": "Chào bạnMình kiểm tra bản IOS 11 sử dụng khá tốt và ổn định bạn có thể cập nhật cho máy nhé.Thân chào bạn.",
      "relate_q_q": -1
    },
    {
      "score": 19.095106,
      "id": "24194591",
      "field_search": "question",
      "question": "Iphone 6 32g bản 2017 này tích hợp sẵn ios 11.0.3 nên còn gặp khá nhiều lỗi....mà nâng lên 11.2.1 thì mình lại càng sợ...bối rối quá ( Tiếc là ko được ios 10 như thông tin ở trên....",
      "answer": "Chào bạn,Dạ còn tùy vào thời gian sản xuất mà máy sẽ được hãng mặc định trang bị phiên bản khác nhau đó ạ. Theo trãi nghiệm của mình thì phiên bản IOS 11.2.1 mới nhất hiện khá ổn định trên iPhone 6 nên bạn có thể yên tâm nâng cấp bạn nhé.Xin thông tin đến bạn.",
      "relate_q_q": 1
    },
    {
      "score": 19.080696,
      "id": "23230568",
      "field_search": "question",
      "question": "Cho mình hỏi máy mình cài sẵn ios 11, mình k biết chức năng chỉnh tông màu của màn hình cho bớt ám vàng chổ nào. Tgdd có hỗ trợ xuống ios 10 k. Cám ơn!",
      "answer": "Chào bạn, Điện thoại này hãng Apple không còn cho hạ xuống iOS 10 nữa nên không xuống được bạn nhé .Để chỉnh tông màu màn hình bạn vào cài đặt > màn hình và độ sáng > Nigh Shift > tắt nhé bạn .Thông tin đến bạn .",
      "relate_q_q": -1
    },
    {
      "score": 19.078526,
      "id": "28736674",
      "field_search": "question",
      "question": "Cho hỏi ip 6 giờ ios mấy vậy",
      "answer": "Chào bạn,Dạ hiện máy được hỗ trợ cập nhật lên cao nhất iOS 11.4 bạn nhé.Xin thông tin đến bạn.",
      "relate_q_q": 2
    },
    {
      "score": 19.025972,
      "id": "24819049",
      "field_search": "question",
      "question": "Ios bản beta là sao vậy QTV",
      "answer": "Chào bạn,Trường hợp này bạn vui lòng chụp lại ảnh màn hình rồi up lên để mình kiểm tra và hỗ trợ giúp bạn chính xác hơn nha.Mong phản hồi từ bạn.",
      "relate_q_q": -1
    },
    {
      "score": 19.0,
      "id": "24446669",
      "field_search": "question",
      "question": "- Iphone 6 ở chỗ mik đây là chạy HĐH iOS  10 hay 11 vậy ạ.  Nếu là iOS 11 thì máy có chạy nhanh k ?",
      "answer": "Chào bạn, iPhone 6 32GB có cấu hình đáp ứng được IOS 11 và tùy vào từng đợt nhập hàng mà đã được nhà sản xuất hỗ trợ cập nhật các phiên bản IOS khác nhau và máy nguyên Seal nên mình không thể kiểm tra cho bạn được mong bạn thông cảm nhé. Xin thông tin đến bạn ạ !",
      "relate_q_q": 2
    },
    {
      "score": 18.980515,
      "id": "24383656",
      "field_search": "question",
      "question": "Cho mình hỏi iphone 6 có phiên bản ios 10 không ad",
      "answer": "Chào bạn,Trường hợp này thì tùy vào từng lô hàng bạn nha. Các lô hàng mới thì sẽ chạy các phiên bản iOS mới hơn và ngược lại bạn nhé. Thân chào bạn !",
      "relate_q_q": -1
    },
    {
      "score": 18.920635,
      "id": "23295401",
      "field_search": "question",
      "question": "M mới mua ip6 32g ở TGDD. Cho m IOS 10 hay IOS 11 cái nào cho hiệu suất xử lí tốt và pị bền hơn vậy. Mới chuyển từ android qua ios nên ko biết.",
      "answer": "Chào bạn, Với độ bền của máy thì sẽ tùy vào cách bảo quản của người dùng còn hệ điều hành IOS 11 thì sẽ tối ưu hơn bảo mật hơn, nhiều tính năng hơn nhưng sẽ nặng và hao pin hơn nhưng không nhiều và khi đã cập nhật thì không quay về IOS 10 được nha bạn. Thân chào bạn !",
      "relate_q_q": -1
    },
    {
      "score": 18.821716,
      "id": "27729479",
      "field_search": "question",
      "question": "Cho em hỏi hệ điều hành của máy lúc mua là IOS 11 sẵn rồi ạ? Hay là mua xong mới bắt đầu nâng cấp?",
      "answer": "Chào bạn,Dạ phiên bản iOS thì tuỳ thuộc vào lô hàng bạn nha. Với các lô hàng mới thì máy sẽ được cài đặt sẵn iOS 11 bạn nhé. Xin thông tin đến bạn ạ !",
      "relate_q_q": 1
    },
    {
      "score": 18.799812,
      "id": "24299266",
      "field_search": "question",
      "question": "Shop cho hỏi máy giờ mở hộp là máy chạy ios 10 hay 11 vậy?",
      "answer": "Chào anh,Hiện tại em không thể kiếm tra được là máy ios 10 hay 11 nhưng các đơn hàng sau này sẽ có ios 11 ạ, nhưng được tối ưu tốt nên chạy rất mượt và nhanh nha.Thông tin đến anh.",
      "relate_q_q": 2
    },
    {
      "score": 18.792894,
      "id": "28893968",
      "field_search": "question",
      "question": "Ip6 này chạy ios 11 chấm mấy v qtv",
      "answer": "Chào bạn,Dạ trường hợp này còn tùy vào lô hàng của hãng sản xuất cung cấp nữa nha bạn. Tuy nhiên thường thì máy mới chạy IOS 11.2 bạn nhé.Xin thông tin đến bạn ạ !",
      "relate_q_q": 1
    },
    {
      "score": 18.792418,
      "id": "28268197",
      "field_search": "question",
      "question": "Mình hỏi chút ios11.4 có hạ được về ios10 hay ios 9 không ạ",
      "answer": "Chào bạn Trường hợp này rất tiếc khi bạn đã nâng cấp máy lên iOS cao thì Apple không hỗ trợ hạ cấp máy về iOS thấp được nữa bạn nhé . Thông tin đến bạn .",
      "relate_q_q": -1
    },
    {
      "score": 18.765009,
      "id": "22757745",
      "field_search": "question",
      "question": "Cho mình hỏi. Ios 10.3.3 có bị khóa chưa vậy, và ios 11.0.3 có về được ios 10.3.3 ko vậy qtv. Thanks",
      "answer": "Chào bạn,Phiên bản iOS 10.3.3 hiện đã bị khóa, nên không thể hạ về được iOS 10.3.3 được nữa bạn nhé. Thân chào bạn !",
      "relate_q_q": -1
    },
    {
      "score": 18.71793,
      "id": "27570751",
      "field_search": "question",
      "question": "Cho mình hỏi iPhone 6splus nếu mua mà kích hoạt thì sẽ chạy luon iOS hiện tại hay là iOS 9.0 ạ",
      "answer": "Chào anh,Dạ hiện sản phẩm này đang được kinh doanh tại Thegioididong.com  với bản rom iOS 11 đó anh nha.Chia sẻ cùng anh.",
      "relate_q_q": 1
    },
    {
      "score": 18.689144,
      "id": "26639851",
      "field_search": "question",
      "question": "máy iphone 6 mới chay ios mấy vậy",
      "answer": "Chào bạn,Mình kiểm tra nếu bạn mua các sản phẩm Iphone 6 mới thì máy sẽ dùng bản IOS 11 bạn nhé.Thông tin đến bạn.",
      "relate_q_q": 2
    },
    {
      "score": 18.664675,
      "id": "27385845",
      "field_search": "question",
      "question": "máy này chạy mượt mấy game như modern combat 5, vainglory k qtv ? Bản ios 11 có lag k qtv ?",
      "answer": "Chào bạn, Theo mình thấy thì máy sử dụng ios 11 tương đối ổn định bạn nhé. Máy có thể chơi được modern combat 5, vainglory. Tuy nhiên bạn nên đóng hết ứng dụng ngầm giúp máy chạy mượt hơn nha bạn Thân chào bạn!",
      "relate_q_q": -1
    },
    {
      "score": 18.648335,
      "id": "25062871",
      "field_search": "question",
      "question": "cko m hoi tgdd co jup ha ios 11 xuong 10 hay 9 k ak",
      "answer": "Chào bạn.Dạ rất tiếc thì không được ạ khi đã nâng cấp thì không hạ cấp được nữa bạn nhé. Thông tin đến bạn.",
      "relate_q_q": -1
    },
    {
      "score": 18.58936,
      "id": "26750484",
      "field_search": "question",
      "question": "Em xin hỏi là dòng iphone 6 này còn phiên bản ios 10 không ạ...",
      "answer": "Chào bạn, Điện thoại iPhone 6 32GB bạn mua mới bên mình là lô hàng mới và chạy sẵn iOS 11 rồi bạn nhé. Thông tin đến bạn .",
      "relate_q_q": -1
    },
    {
      "score": 18.555828,
      "id": "27385831",
      "field_search": "question",
      "question": "máy này chạy mượt mấy game như modern combat 5, vainglory k qtv ? Bản ios 11 có lag k qtv ?",
      "answer": "Chào bạn, Điện thoại iPhone 6 32GB chơi tốt các game trên bạn nhé .Máy dùng hệ điều hành iOS 11 thỉnh thoảng cũng có giật lag khi dùng ứng dụng nặng nhé bạn.Thông tin đến bạn .",
      "relate_q_q": -1
    },
    {
      "score": 18.5017,
      "id": "21770123",
      "field_search": "question",
      "question": "AD cho em hỏi E muốn hạ từ IOS 10 Xuống IOS 9 Thì thế giới di động có làm kh ạ Làm thì mất phí bao nhiêu",
      "answer": "Chào bạn,Rất tiếc, hiện tại bạn không thể hạ cấp xuống iOS 9 được nữa bạn nhé. Thân chào bạn !",
      "relate_q_q": -1
    },
    {
      "score": 18.48779,
      "id": "31554954",
      "field_search": "question",
      "question": "iphone 6 32gb mới hiện tại ios 11 hay 12 vậy ạ",
      "answer": "Chào anh , Dạ còn tùy vào lô hàng mới hay cũ mà sẽ chạy hệ điều hành iOS 11 hay 12 anh nhé. Đa phần các lô hàng mới bên em đều chạy hệ điều hành IOS 12 cả ạ. Khi mua anh có thể nhờ các bạn tại siêu thị hỗ trợ thêm ạ. Thông tin đến anh .",
      "relate_q_q": 2
    },
    {
      "score": 18.46084,
      "id": "24306725",
      "field_search": "question",
      "question": "Mình đang dùng ip6 32gb, ở phiên bản 10.3.2, giờ muốn lên 10.3.3 được không. Hay là sẽ phải lên ios 11?( bạn có thể đánh giá 2 bản ios 10 ở trên được không?) Cám ơn bạn nhiều!",
      "answer": "Chào bạn,Dạ hiện tại nếu nâng cấp thì mình sẽ lên trực tiếp IOS 11 mới nhất luôn, bản IOS 10 Apple đã khóa lại rồi bạn nhé; mình có thử tìm hiểu một số đánh giá từ phía người dùng thì bản IOS 10.3.3 là bản ổn định hơn, do bản này cập nhật một số dữ liệu giúp vá lỗi từ bản cũ đó ạ; nếu bạn đang ở bản IOS 10 cũ mình khuyên bạn nên cân nhắc về việc cập nhật mới bạn nhé; mình sẽ không về lại bản cũ được nữa bạn nha.Chia sẻ cùng bạn!",
      "relate_q_q": -1
    },
    {
      "score": 18.40044,
      "id": "26631381",
      "field_search": "question",
      "question": "Máy ip6 này giờ kích hoạt thì chạy ios mấy vậy add?",
      "answer": "Chào bạn, Trường hợp này thì sẽ tùy vào từng đợt nhập hàng mà sẽ có các phiên bản hệ điều hành IOS khác nhau nha bạn và máy được hỗ trợ cập nhật IOS cao nhất hiện tại là IOS 11.3 nha bạn.Xin thông tin đến bạn ạ !",
      "relate_q_q": 2
    },
    {
      "score": 18.358574,
      "id": "28953181",
      "field_search": "question",
      "question": "Ip6 này chạy ios 11 chấm mấy v qtv",
      "answer": "Chào bạn,Trường hợp này thì còn tùy vào lô hàng mà máy sẽ có phiên bản IOS tương ứng và máy nguyên seal nên rất tiếc mình cũng chưa thể xác định cụ thể là máy khi khui ra sẽ chạy phiên bản IOS 11 nào bạn nhé, mong bạn thông cảm.Thông tin đến bạn !",
      "relate_q_q": 1
    },
    {
      "score": 18.345812,
      "id": "27010295",
      "field_search": "question",
      "question": "qtv cho hoi lam ha xuog ios 8 vay",
      "answer": "Chào bạn, Rất tiếc, Apple đã khóa và không cho phép hạ nên không thể hạ được nha bạn.Xin thông tin đến bạn ạ !",
      "relate_q_q": -1
    },
    {
      "score": 18.33466,
      "id": "26122654",
      "field_search": "question",
      "question": "Mạy chạy ios 10 hay ios 11 ad",
      "answer": "Chào anh Hiện em kiểm tra thì sản phẩm chạy IOS 11 anh nhé.Xin gửi thông tin đến anh.",
      "relate_q_q": 2
    },
    {
      "score": 18.31786,
      "id": "19924190",
      "field_search": "question",
      "question": "cho em hỏi em muốn xác nhận tính tin cậy cho iphone ios 8 khi cài đặt ứng dụng thì làm ntn ạ",
      "answer": "Chào bạn,Trường hợp này thì bạn vào cài đặt > cài đặt chung > quản lý cấu hình và thiết bị > chọn ứng dụng > chọn tin cậy bạn nhé. Thân chào bạn !",
      "relate_q_q": -1
    },
    {
      "score": 18.315645,
      "id": "19935081",
      "field_search": "question",
      "question": "QTV cho hỏi iphone 6,6s,6splus bản 32gb 2017 là bản quốc tế hay bản Vn/a vậy",
      "answer": "Chào anh,Dạ các sản phẩm iphone này bên em kinh doanh là phiên bản quốc tế anh nhé.Thông tin đến anh!",
      "relate_q_q": -1
    },
    {
      "score": 18.275589,
      "id": "23427303",
      "field_search": "question",
      "question": "Iphone 6 hiện đang chạy ios 10 chấm mấy vậy ạ ?",
      "answer": "Chào bạn,Dạ sẽ tùy lô hàng khác nhau mà máy sẽ có phiên bản iOS khác nhau bạn nhé. Nên rất tiếc là mình chưa có kiểm tra chính xác giúp bạn được nha.Thông tin đến bạn!",
      "relate_q_q": 1
    },
    {
      "score": 18.222626,
      "id": "26505983",
      "field_search": "question",
      "question": "mình muốn mua iphone 6 tại TGDD, cho hỏi trc là nếu xài iP6 thì iOS mấy là ổn?",
      "answer": "Chào bạn,Dạ iPhone 6 hiện vẫn chạy tốt IOS 10 và IOS 11 bạn nhé.Xin thông tin đến bạn.",
      "relate_q_q": -1
    },
    {
      "score": 18.216553,
      "id": "23378773",
      "field_search": "question",
      "question": "Iphone 6 mới hiện đang chạy ios mấy vậy?",
      "answer": "Chào anh !  Iphone 6 mới hiện đang ở bản IOS 10 anh nhé.Thông tin đến anh.",
      "relate_q_q": 2
    },
    {
      "score": 18.153027,
      "id": "22844040",
      "field_search": "question",
      "question": "QTV cho e hỏi là nếu e mới mua máy mà cập nhật lên IOS 11.0.3 thì máy có bị lag k ạ",
      "answer": "Chào bạn,Với phiên bản iOS 11 thì đã khá ổn định, nên khi bạn nâng cấp lên thì máy sẽ không bị lag bạn nhé.Thông tin đến bạn!",
      "relate_q_q": -1
    },
    {
      "score": 18.138866,
      "id": "23550045",
      "field_search": "question",
      "question": "Máy mới chạy hệ điều hành ios mấy vậy",
      "answer": "Chào anh, Trường hợp của anh tùy vào lô hàng tuy nhiên đa số đều đã được cập nhật lên phiên bản iOS mới nhất anh nhé. Nếu anh quan tâm vui lòng cung cấp thông tin khu vực cụ thể để bên em có thể kiểm tra siêu thị có hàng gần nhất giúp anh tốt hơn ạ.  Mong sớm nhận phản hồi từ anh!",
      "relate_q_q": 2
    },
    {
      "score": 18.069641,
      "id": "21283706",
      "field_search": "question",
      "question": "Cho em gỏi lúc mới mua máy sẽ có hệ điều hành ios mấy vậy",
      "answer": "Chào bạn Trường hợp này sẽ tùy thuộc lô hàng nhưng đa phần là máy sẽ được cập nhật lên iOS mới nhất 10.3.3 bạn nhé .Thông tin đến bạn .",
      "relate_q_q": 2
    },
    {
      "score": 18.069637,
      "id": "19618583",
      "field_search": "question",
      "question": "QTV Cho em hỏi iphone 6 đang chạy ios 10.3.2 giờ hạ xuống ios 10.3.1 được không vậy",
      "answer": "Chào bạn, Hạ được bạn nhé, bạn có thể kết nối điện thoại với itunes , bạn dùng phần mềm này Restore lại hệ điều hành iOS 10.3.1 cho máy là được nhé bạn . Thông tin đến bạn .",
      "relate_q_q": -1
    },
    {
      "score": 17.955406,
      "id": "27303950",
      "field_search": "question",
      "question": "Máy đang dùng là ios 11 giờ muốn hạ xuống ios 10 được k qtv",
      "answer": "Chào bạn,Rất tiếc là không hạ cấp được IOS nữa bạn nhé.Thông tin đến bạn !",
      "relate_q_q": -1
    },
    {
      "score": 17.92687,
      "id": "19256979",
      "field_search": "question",
      "question": "Cho em hỏi là Ip6 hệ điều hành IOS 8 mà sao o đây để IOS 10 Vậy có sự nhầm lẫn về thông tin cấu hình Sp ko vậy ạ.",
      "answer": "Chào bạn, Trường hợp này thì với các đợt nhập hàng sau thì đã được nhà sản xuất hỗ trợ cập nhật sản IOS 10 nha bạn và còn về pin thì sẽ tùy vào nhu cầu sử dụng của bạn nếu bạn sử dụng 3G để lướt web liên tục thì được khoảng 3 - 4h với wifi thì được khoảng 4 - 5h nha bạn. Thân chào bạn !",
      "relate_q_q": -1
    },
    {
      "score": 17.853165,
      "id": "19391125",
      "field_search": "question",
      "question": "Lúc mới mua may cai ios mấy aj",
      "answer": "Chào anh! Sản phẩm hiện tại được cài hệ điều hành ios 10 anh nhé, Nếu anh quan tâm sản phẩm thì anh vui lòng cho em xin thông tin địa chỉ anh đang sống (quận/ huyện, tỉnh) để em tìm kiếm hàng giúp  anh.Mong  nhận phản hồi  sớm từ anh.",
      "relate_q_q": 2
    },
    {
      "score": 17.819756,
      "id": "19680987",
      "field_search": "question",
      "question": "Iphone 5s của mình đang ở ios 9.3.2 nếu factory reset thì sẽ về ios mấy?,",
      "answer": "Chào bạn,Thao tác này không hạ IOS của máy xuống bạn nhé. Thông tin đến bạn !",
      "relate_q_q": -1
    },
    {
      "score": 17.815193,
      "id": "17942122",
      "field_search": "question",
      "question": "Iphone 6 32 Gb chạy iOS 10 điểm antutu được khoảng bao nhiêu vậy QTV",
      "answer": "Chào bạn,Dạ với sản phẩm iPhone 6, thì có điểm Antutu khoảng 79215 bạn nhéThân chào bạn !",
      "relate_q_q": -1
    },
    {
      "score": 17.769285,
      "id": "23661563",
      "field_search": "question",
      "question": "Alo admin cho mình hỏi ip6 ios mấy máy mới khui",
      "answer": "Chào chị, Trường hợp của chị sẽ tùy lô hàng tuy nhiên đa số đã được cập nhật lên iOS mới nhất rồi chị nhé. Nếu chị quan tâm vui lòng đến siêu thị Thegioididong.com có hàng gần nhất để trải nghiệm sản phẩm cũng như mua hàng ạ. Thân chào chị!",
      "relate_q_q": 2
    },
    {
      "score": 17.674511,
      "id": "17837494",
      "field_search": "question",
      "question": "Sao không là iOS 9 mà bay lên IOS 10 nhỉ,  như vậy sẽ nặng máy lắm,  thao tác không mượt ad?",
      "answer": "Chào bạn, Hiện tại với phiên bản mới nhất là IOS 10 cho nên các dòng sản phẩm lô hàng mới hỗ trợ cập nhật phiên bản mới, với phiên bản này theo mình đánh giá máy sử dụng khá mượt không bị lag nhé bạn.Thân chào bạn! ",
      "relate_q_q": -1
    },
    {
      "score": 17.655638,
      "id": "23540355",
      "field_search": "question",
      "question": "Da ơi cho mình hỏi iPhone 6 ios 11 có xuống được ios 10 k ạ",
      "answer": "Chào bạn Trường hợp này rất tiếc khi bạn đã nâng cấp máy lên iOS 11 thì Apple không hỗ trợ hạ cấp máy iPhone 6 về iOS 10 được nữa bạn nhé . Thông tin đến bạn .",
      "relate_q_q": -1
    },
    {
      "score": 17.639626,
      "id": "23379745",
      "field_search": "question",
      "question": "e mới mua máy va kiểm tra thấy máy chay ios 11 là sao v qtv ? E tưởng ios 10 chứ .",
      "answer": "Chào bạn,Do máy bạn là máy mới được sản xuất gần đây nên đã được nhà sản xuất cài đặt mặc định lên phiên bản cao hơn và nhà sản xuất cũng không tiết lộ vấn đề này với bên mình nên đây là bình thường và bên mình cũng không có cách nào kiểm tra được bạn nha.Mong bạn thông cảm cho sự bất tiện này.",
      "relate_q_q": 1
    },
    {
      "score": 17.636522,
      "id": "27488540",
      "field_search": "question",
      "question": "iphone 6 32gb mua cai ios 10 dc ko",
      "answer": "Chào anh, Với sản phẩm này bên em kinh doanh cài sẳn IOS 11 rồi ạ , không có IOS 10 anh nhé . Thông tin đến anh.",
      "relate_q_q": -1
    },
    {
      "score": 17.635536,
      "id": "26302218",
      "field_search": "question",
      "question": "Tôi đang dùng ip6 bản ios 11.0.1 bản này dùng hơi dơ pin tuột cũng hơi nhanh xíu thế có nên lên bản ios mới k ios 11.3",
      "answer": "Chào bạn Trường hợp này bạn nên cập nhật máy lên iOS 11.3 để máy hoạt động ổn định hơn , Pin cũng ít hao hơn bạn nhé .Thông tin đến bạn .",
      "relate_q_q": -1
    },
    {
      "score": 17.609337,
      "id": "25101170",
      "field_search": "question",
      "question": "Ak ơi  iOS 11 Nieu ek mua con này thì Ben ak có cách nào xuống iOS. 10 k ak ek muốn mua iPhone 6 mà chạy iOS 10 a",
      "answer": "Chào bạn, Rất tiếc là hãng chỉ hỗ trợ người dùng nâng cấp hệ điều hành lên, chứ không hỗ trợ hạ xuống nên bên mình không hỗ trợ hạ được bạn nhé. Mong bạn thông cảm nha  Thân chào bạn!",
      "relate_q_q": -1
    },
    {
      "score": 17.608797,
      "id": "24812858",
      "field_search": "question",
      "question": "Ad cho e hỏi.e đang xài ip 6s nếu mình restore xoá tất cả và cài đặt lại thì nó có tự úp lên phiên bản IOS mới không ạ.e đang ở phiên bản IOS 10.3.2 nên không muốn lên phiên bản mới.mong ad tư vấn giúp.e cảm ơn",
      "answer": "Chào bạn,",
      "relate_q_q": -1
    },
    {
      "score": 17.568283,
      "id": "27169701",
      "field_search": "question",
      "question": "máy có nên nâng cấp lên ios 11.3.1 cho ip6 ko , hay dùng lại phiên bản củ vậy qtv",
      "answer": "dang phiên bản 11.0.3 có nen nang cấp 11.3.1 ko vậy qtv",
      "relate_q_q": -1
    },
    {
      "score": 17.489048,
      "id": "28560727",
      "field_search": "question",
      "question": "Qtv cho e hỏi ios 12 có bản chính thứac chưa ạ",
      "answer": "Chào bạn,",
      "relate_q_q": -1
    },
    {
      "score": 17.478365,
      "id": "25584322",
      "field_search": "question",
      "question": "iPhone 6 tôi dang chạy ios 11.0.2, giờ máy có yêu cầu phiên bản ios 11.2.6. Vậy tôi có nên cập nhật hay không vậy qtv?",
      "answer": "Chào bạn,Trường hợp sản phẩm iPhone 6 khi có thông báo cập nhật phần mềm, bạn nên nâng cấp để được fix các lỗi nhỏ trong quá trình sử dụng, từ đó máy có thể hoạt động ổn định hơn bạn nhé. Thân chào bạn !",
      "relate_q_q": -1
    },
    {
      "score": 17.44186,
      "id": "26396871",
      "field_search": "question",
      "question": "iPhone 6 32gb tgdd bán ra là ios 11. Mấy vậy",
      "answer": "Chào anh ! Dạ khi anh mua máy này đã được hỗ trợ cài sẵn iOS 11 anh nha.Thông tin đến anh.",
      "relate_q_q": 1
    },
    {
      "score": 17.367855,
      "id": "23346879",
      "field_search": "question",
      "question": "cho em hỏi cập nhật lên IOS 11 có mượt không hay là để IOS 10 tốt hơn v?",
      "answer": "Chào bạn, Điện thoại này bạn nên dùng hệ điều hành iOS 10 là tốt nhất , hệ điều hành iOS 11 máy chạy khá chậm bạn nhé. Thông tin đến bạn .",
      "relate_q_q": -1
    },
    {
      "score": 17.359783,
      "id": "19944680",
      "field_search": "question",
      "question": "Phiên bản ói cài sẵn khi mua máy là bao nhiu ạ?",
      "answer": "Chào bạn, Điện thoại iPhone 6 32GB này khi bạn mua bên mình hiện tại được cài sẵn hệ điều hành iOS 10 bạn nhé. Thân chào bạn !",
      "relate_q_q": 2
    },
    {
      "score": 17.32047,
      "id": "25641211",
      "field_search": "question",
      "question": "Cho mình hỏi giờ mình muốn hạ từ ios 11.2 xuống ios 10 cho ip 6plus được không ạ?",
      "answer": "Chào bạn.Dạ rất tiếc thì Apple đã khóa lại rồi không cho hạ cấp được nữa bạn nhé. Thông tin đến bạn.",
      "relate_q_q": -1
    },
    {
      "score": 17.28279,
      "id": "21814884",
      "field_search": "question",
      "question": "Bản ios 11 phát hành trên iphone 6 32GB chưa qtv ơi 😘😘😘😘😘",
      "answer": "Chào bạn,Hiện tại thì bản IOS 11 vẫn chưa có chính thức, theo thông tin mình tìm hiểu thì có thể ngày mai là sẽ có bản cập nhật này bạn nhé.Thông tin đến bạn !",
      "relate_q_q": -1
    },
    {
      "score": 17.271852,
      "id": "25513193",
      "field_search": "question",
      "question": "Em có 9 triệu thì nên mua mới ip6 32gb hay mua cũ ip 6s plus 32gb ạ?",
      "answer": "Chào chị Trang,Nếu chị không ngại mua máy đổi trả thì nên chọn Iphone 6s plus sẽ tốt hơn nhiều chị nhé. Cấu hình, camera, pin của Iphone 6s plus đều nhỉnh hơn nên hỗ trợ giải trí tốt hơn nhiều đó ạ, nên chọn các máy đổi trả còn nhiều thời gian bảo hành chính hãng có thể sẽ ít trầy xước hơn.Thông tin đến chị.",
      "relate_q_q": -1
    },
    {
      "score": 17.26934,
      "id": "21874334",
      "field_search": "question",
      "question": "QTV cho hỏi: Mình muốn Restore lại Iphone qua Itunes. Máy mình hiện tại đang ở ios 10.3.3. Vậy khi Restore xong qua itunes thì iphone sẽ ở phiên bản hiện tại là 10.3.3 hay sẽ tự động lên ios 11 mới nhất? Thank",
      "answer": "Chào bạn, Khi bạn restore máy qua itunes, thì máy sẽ cập nhật lên ios 11 bạn nhé Thân chào bạn!",
      "relate_q_q": -1
    },
    {
      "score": 17.247677,
      "id": "27875847",
      "field_search": "question",
      "question": "Hiện tôi muốn mua iphone6 32gb tại cửa hàng là sử dụng hệ điều hành ios 10 hay 11 vậy TGDĐ?",
      "answer": "Chào bạn, Hệ điều hành hiện tại của sản phẩm  này là iOS 11 bạn nhé. Thông tin đến bạn.",
      "relate_q_q": 2
    },
    {
      "score": 17.221127,
      "id": "25437487",
      "field_search": "question",
      "question": "Ad ơi Iphone 6 32GB đang chạy IOS mấy vậy,  IOS đó có lag k ad",
      "answer": "Chào bạn,Máy này hiện đang sử dụng  iOS 11 và hệ điều hành này hiện không có tình trạng bị lag bạn nha.Xin thông tin đến bạn!",
      "relate_q_q": 2
    },
    {
      "score": 17.214819,
      "id": "20573465",
      "field_search": "question",
      "question": "Iphone 6 này chạy ios 10 chấm bao nhiêu vậy",
      "answer": "Chào bạn,Trường hợp này thì tùy vào lô hàng của sản phẩm bạn nha. Các lô hàng mới hơn sẽ được cập nhật phiên bản iOS cao hơn, nên mình không thể thông tin chính xác cho bạn được. Mong bạn thông cảm nhé.Thân chào bạn !",
      "relate_q_q": 1
    },
    {
      "score": 17.146755,
      "id": "27894563",
      "field_search": "question",
      "question": "Máy iphone 6 . 32 này mới thì  chạy ios 11 mấy ạ .của mình sao lại 11.4",
      "answer": "Chào bạn,Trường hợp này thì tùy vào lô hàng bạn nha, với các lô hàng mới hơn thì máy sẽ được cài đặt sẵn iOS cao hơn bạn nhé. Xin thông tin đến bạn ạ !",
      "relate_q_q": 1
    },
    {
      "score": 17.06752,
      "id": "27121992",
      "field_search": "question",
      "question": "Mình mới mua máy 1 tuần  lúc mua máy có sẵn ios 11.3 . Mình vừa mở máy lên thì nó yêu cầu cập nhật lên ios 11.3.1 mình bấm để sau thì nó ghi là sẽ tự update nếu mình sạc từ 23h đến 5h sáng , mình mới xài k bt cái này là gì hết . Cho mình hỏi luôn là ios 11.3.1 có mượt như ios 11.3 k ? Mong ad trả lời sớm",
      "answer": "Chào bạn, Theo mình thấy thì bản cập nhật này giúp:-Cải thiện tính bảo mật của iPhone/ iPad.-Sửa lỗi không sử dụng được cảm ứng trên iPhone 8 nếu như bị thay bằng màn hình không chính hãng.Ngoài ra, máy sẽ tự update nếu bạn cắm sạc trong khoảng thời gian từ 23h đến 5h sáng và có kết nối wifi bạn nhé Thân chào bạn!",
      "relate_q_q": -1
    },
    {
      "score": 17.05992,
      "id": "19489561",
      "field_search": "question",
      "question": "Ip6 32gb ở tgdd khi mua thuong dduoc cai ios 10 chấm mây vậy ạ",
      "answer": "Chào bạn,Dạ tùy theo thời điểm kích hoạt sẽ có phiên bản khác nhau ạ; do đây là máy nguyên seal, chỉ ưu tiên cho khách hàng nên rất xin lỗi bạn mình không có thông tin chính xác bạn nhé.Chia sẻ cùng bạn!",
      "relate_q_q": 1
    },
    {
      "score": 17.046354,
      "id": "30568363",
      "field_search": "question",
      "question": "Cho em hỏi là làm sao để nâng cấp từ ios 7.1.2 lên ios 9 của ip 4 vậy ạ",
      "answer": "Chào anh ,Rất tiếc là máy không hỗ trợ nâng cấp lên iOS 9 anh nhé.Xin thông tin đến anh .",
      "relate_q_q": -1
    },
    {
      "score": 16.974068,
      "id": "27163983",
      "field_search": "question",
      "question": "Iphone 6 mình còn bản ios 10 không ạ?",
      "answer": "Chào anh,Rất tiếc bên em hiện chỉ có Điện thoại iPhone 6 32GB Ios 11 thôi anh nhé, Anh có thể cho em xin thêm thông tin (quận, huyện, tỉnh) mà mình có thể đến mua sản phẩm để em kiểm tra hiện còn hàng hay không ạ?Mong phản hồi sớm từ anh!",
      "relate_q_q": -1
    },
    {
      "score": 16.950659,
      "id": "22766038",
      "field_search": "question",
      "question": "giờ mua thì máy chạy ios 10.3.3 hay 11 vậy",
      "answer": "Chào anh,Sản phẩm trên lúc mua có thể là ios 10 ạ, vì ios 11 mới ra nên các lô hàng này có thể chưa được apple cập nhật lên ios 11 đâu ạ.Thông tin đến anh.",
      "relate_q_q": 1
    },
    {
      "score": 16.942188,
      "id": "24655429",
      "field_search": "question",
      "question": "Iphone 6 ios 11 có suống ios 10 được không",
      "answer": "Chào anh! Dạ. Hệ điều hành nâng lên rồi thì không hạ xuống được ạ. Thông tin đến anh!",
      "relate_q_q": -1
    },
    {
      "score": 16.900242,
      "id": "19528018",
      "field_search": "question",
      "question": "Iphone 6 32gb này. Có mấy màu vậy qtv ?",
      "answer": "Chào chị,Sản phẩm iPhone 6 32GB hiện bên em chỉ có màu Vàng đồng thôi chị nha, không biết hiện chị đang ở khu vực nào (quận,huyện) để em có thể tìm siêu thị có hàng, thuận tiện nhất để chị trải nghiệm sản phẩm nha. Mong phản hồi từ chị!",
      "relate_q_q": -1
    },
    {
      "score": 16.818743,
      "id": "23855052",
      "field_search": "question",
      "question": "Cho hoi ios 11 co suông được ios10 hoac 9 khong add",
      "answer": "Chào anh!  Dạ. Hệ điều hành nâng lên rồi thì không hạ xuống được ạ. Thông tin đến anh!",
      "relate_q_q": -1
    },
    {
      "score": 16.781567,
      "id": "23916157",
      "field_search": "question",
      "question": "Cho mình hỏi iphone 6 ở mình là đang ở hệ điều hành ios 10 hay ios 11 ạ, mình xem ở ngoài là ios 11 nhưng vào trong xem chi tiết lại ghi ios 10",
      "answer": "Chào bạn.Dạ trường hợp này thì bên mình không thể kiểm tra chính xác được bạn nhé. Vì tùy vào từng lô hàng đợt hàng về từ Apple sẽ có máy là ios 10 máy là ios 11 đó ạ. Thông tin đến bạn.",
      "relate_q_q": 1
    },
    {
      "score": 16.740969,
      "id": "26661195",
      "field_search": "question",
      "question": "Cho mình hỏi, iphone 6 32G lúc mới active sẽ sử dụng ios mấy?",
      "answer": "Chào bạn,Điện thoại iPhone 6 32GB hiện tại mới Active sử dụng chạy IOS 11 bạn nhé.Thân chào bạn !",
      "relate_q_q": 2
    },
    {
      "score": 16.707777,
      "id": "17858939",
      "field_search": "question",
      "question": "Máy 6 32gb này là bản quốc tế hay bản nội địa vậy",
      "answer": "Chào anh Duy,Dạ với các máy Iphone được Thegioididong.com là bản quốc tế được phân phối tại thị trường Việt Nam anh nha.Thân ái đến anh ạ!",
      "relate_q_q": -1
    },
    {
      "score": 16.70287,
      "id": "26674839",
      "field_search": "question",
      "question": "Cho em hỏi chuyên viên tgdd giúp em hạ ios 11 xuống ios 10 được ko ạ Máy lên ios 11 lag quá ạ",
      "answer": "Chào bạn,Rất tiếc Apple đã khóa hạ cấp xuống iOS 10 nên không thể hạ được trên máy bạn nhé. Mong bạn thông cảm cho sự bất tiện này.Thân chào bạn !",
      "relate_q_q": -1
    },
    {
      "score": 16.530975,
      "id": "24484200",
      "field_search": "question",
      "question": "Ios ip6 hiện tai là 10 hay 11",
      "answer": "Chào anh !  Dạ hiện thì sản phẩm đang ở IOS 10 đó anh. Tuy nhiên trường hợp này còn tuỳ vào lô nhập hàng thì được nhà sản xuất hỗ trợ cập nhật bản IOS khác nhau nên bên em không kiểm tra chính xác được anh nhé.Thông tin đến anh.",
      "relate_q_q": 2
    },
    {
      "score": 16.513538,
      "id": "22831996",
      "field_search": "question",
      "question": "cho hỏi là những ip mấy thì có bản jetblack vậy",
      "answer": "Chào chị.Với sản phẩm Điện thoại iPhone  thì bản Điện thoại và bản Điện thoại  có bản jet black chị nhé.Thông tin đến chị.",
      "relate_q_q": -1
    },
    {
      "score": 16.485056,
      "id": "21800443",
      "field_search": "question",
      "question": "qtv cho mình hỏi, mình mua máy ip 6s plus ngày 10/9/2017 mới đây và được cấp thẻ tín dụng tính ra cũng dc 8 ngày rồi mik chưa nhận được thẻ FE CREDIT từ bưu điện, qtv vui lòng kiểm tra giúp mik ạ",
      "answer": "Chào chị Về trường hợp của chị, chị vui lòng liên hệ trực tiếp công ty tài chính để được hỗ trợ chị nha. Số điện thoại của công ty tài chính FECredit là:  1900 545 415.Thông tin đến chị !",
      "relate_q_q": -1
    },
    {
      "score": 16.480946,
      "id": "26871660",
      "field_search": "question",
      "question": "Cho e hỏi nếu dùng lâu dài để chơi game thì nên đung hdh android hay ios ạ",
      "answer": "Chào bạn, Hệ điều hành iOS là hệ điều hành ổn định , mượt mà và là hệ điều hành dùng cho chơi game tốt nhất bạn nhé. Thông tin đến bạn .",
      "relate_q_q": -1
    },
    {
      "score": 16.456633,
      "id": "18239140",
      "field_search": "question",
      "question": "Iphone 4 có cài đc ios 8.1 k qtv",
      "answer": "Chào bạn,Với sản phẩm iPhone 4 thì không cài đặt phiên bản iOS 8.1 bạn nhé. Thân chào bạn !",
      "relate_q_q": -1
    },
    {
      "score": 16.436008,
      "id": "24716584",
      "field_search": "question",
      "question": "Xin chào cho mình hỏi ip6 thường dùng bản 11 có xuống đc ios 10 nữa k hay phải chờ ms đc hạ cấp xuống",
      "answer": "Chào bạn,Hiện tại thì không thể quay về iOS 10 được nữa bạn nhé. Thân chào bạn !",
      "relate_q_q": -1
    },
    {
      "score": 16.43077,
      "id": "21865849",
      "field_search": "question",
      "question": "Iphone 6 plus hiện đang chạy hệ điều hành ios mấy? có cần cập nhật phiên bản ios 11 không vậy ad?",
      "answer": "Chào bạn, Điện thoại này bên mính bán đang chạy hệ điều hành iOS 10.3 , bạn có thể cập nhật lên hệ điều hành iOS 11 cho máy được bạn nhé. Thông tin đến bạn .",
      "relate_q_q": 1
    },
    {
      "score": 16.406359,
      "id": "24389654",
      "field_search": "question",
      "question": "Iphone 6 3gb này cập nhật ios 11 có ổn hơn bản 10 k ạ ? Co lag hơn hay hao pin hơn k ạ ?",
      "answer": "Chào bạn,Dạ hiện phiên bản iOS 11 đã khá là ổn định, nên sẽ không có tình trạng lag hay hao pin nhiều so với phiên bản cũ nha.Chia sẻ cùng bạn !",
      "relate_q_q": -1
    },
    {
      "score": 16.387775,
      "id": "26418938",
      "field_search": "question",
      "question": "Ad cho hỏi. Ip 6 32 gb VN/A ra mắt tháng 3/2017 chỉ duy nhất màu gold,dành cho các thị trường đang phát triển. Nhưng ios11 ra mắt tháng 9 /2107, và được cho cập nhật tháng 10/2017! vậy sao ip 6 lại cài ios11.???Phải chăng đây là hàng kich hoạt rồi.Đúng ra là cài ios  thời điểm lúc đó ( 3/2017 ) là 10.3.3 chứ??? Mình muốn mua ip6 2017  vn/a  có ios 10. Thì mua o đâu?",
      "answer": "Chào bạn,Apple có truyền thống cập nhật iOS mới nhất cho lô máy sản xuất gần đây nhất, không tùy thuộc vào máy ra mắt cách iOS ra mắt bao lâu nên iPhone 6 2017 cài đặt iOS 11 là phù hợp chính sách nhà sản xuất,Apple không cài đặt như bạn nghĩ và không có máy có iOS 10 như bạn muốn. Thông tin đến bạn !",
      "relate_q_q": -1
    },
    {
      "score": 16.387112,
      "id": "26440292",
      "field_search": "question",
      "question": "Máy lúc mình mua là iOS 10.2.1 thì thời điểm này mình có cập nhật được lên iOS 10.3.3 không ạ, hay buộc phải cập nhật lên iOS 11 ạ",
      "answer": "Chào bạn, Trường hợp này thì khi bạn cập nhật sẽ lên thẳng IOS 11.3 chứ không cập nhật IOS 10.3.3 được nha bạn.Xin thông tin đến bạn ạ !",
      "relate_q_q": -1
    },
    {
      "score": 16.376995,
      "id": "28428323",
      "field_search": "question",
      "question": "iPhone 6 mới mua được 6 tháng đang ở ios 11.2.6 có nên nâng cấp lên bản mới không?",
      "answer": "Chào bạn,Nếu bạn thấy máy dùng đã tốt rồi thì không cần cập nhật thêm. Còn nếu bạn muốn trải nghiệm những thay đổi mới hơn của phiên bản mới thì có thể cập nhật máy lên nhé.Chia sẻ cùng bạn !",
      "relate_q_q": -1
    },
    {
      "score": 16.347775,
      "id": "27889747",
      "field_search": "question",
      "question": "Đập hộp là ios mấy vậy?",
      "answer": "Chào bạn Đa phần các máy sẽ chạy iOS mới là 11.4 bạn nha .Thông tin đến bạn .",
      "relate_q_q": 2
    },
    {
      "score": 16.324627,
      "id": "32107680",
      "field_search": "question",
      "question": "Cho hỏi nếu mình mua iPhone này về chạy ios 12.1.2 có bị chậm ko ad?",
      "answer": "Chào anh,  Dạ với cấu hình của iPhone 6 thì có thể đáp ứng được tốt IOS 12.1.2 nên anh có thể yên tâm ạ.Xin thông tin đến anh ạ ! ",
      "relate_q_q": -1
    },
    {
      "score": 16.321335,
      "id": "23577046",
      "field_search": "question",
      "question": "Iphone6 32g chạy ios 10 của mình cũng dùng iPhone6 32g mà sao lại chạy ios 11.0.2 vậy QTV",
      "answer": "Chào bạn,Trường hợp này có thể khi bạn mua bạn đã tiến hành cập nhật nên máy sẽ có phiên bản IOS 11.0.2 bạn nhé.Thông tin đến bạn.",
      "relate_q_q": -1
    },
    {
      "score": 16.319908,
      "id": "26738781",
      "field_search": "question",
      "question": "ủa mọi người cho mình hỏi mua máy mới tinh sao lại có cài sẵn hệ điều hành nhỉ, nay mình mua máy mởi ở tgdđ ko để ý về nhà mới nhớ ra là máy đã cài sẵn",
      "answer": "Chào bạn,Smartphone mới nào cũng đều có sẵn hệ điều hành bạn nhé.Xin thông tin đến bạn!",
      "relate_q_q": -1
    },
    {
      "score": 16.294043,
      "id": "31062871",
      "field_search": "question",
      "question": "Cho em hỏi, iphone 6 mới mặc định cài IOS 10 có phải sản xuất trước máy iphone 6 xài IOS 11 phải không ạ? Và nó có bị sản xuất lâu quá rồi không?",
      "answer": "Chào bạn, xin lỗi đã để bạn đợi lâu nhéTheo em thấy thì tùy từng lô hàng, với lô hàng mới thì hãng sẽ cập nhật ios 11 bạn nhé Sản phẩm này ra mắt năm 2014 nhưng hiện tại hãng vẫn sản xuất máy để phù hợp với nhu cầu và phân khúc người dùng tầm trung bạn nhé Thông tin đến bạn ạ!",
      "relate_q_q": -1
    },
    {
      "score": 16.280867,
      "id": "25113986",
      "field_search": "question",
      "question": "QTV cho mình hỏi mình sử dụng Ip6 mới hôm qua nâng lên Ios 11.2.5 tự nhiên touch id vẫn sử dụng bình thường thì sau đó lúc đc lúc ko rồi lại mất luôn vô phần cài đặt thì ko còn vân tay nào. Mà lúc trước chưa nâng lên bản Ios mới thì vân tay sử dụng bt không có chịu chứng chậm hay lúc đc lúc ko. Mong được giải đáp",
      "answer": "Chào bạn,Trường hợp này có thể máy đã bị xung đột phần mềm, bạn vào cài đặt > cài đặt chung > đặt lại > đặt lại tất cả cài đặt (dòng 1) xem khắc phục được không nha bạn. Mong nhận được phản hồi từ bạn !",
      "relate_q_q": -1
    },
    {
      "score": 16.237644,
      "id": "26736883",
      "field_search": "question",
      "question": "Jo mua ip 6 nguyên seal(2017)  liệu còn bản ios 10 ko ạ",
      "answer": "Chào bạn,Dạ mình xem thử trên một số máy mà khách hàng bên mình kích hoạt mới thì đa số là lên IOS 11 hết rồi đó ạ.Chia sẻ cùng bạn!",
      "relate_q_q": -1
    },
    {
      "score": 16.216038,
      "id": "22671176",
      "field_search": "question",
      "question": "cho mình hỏi iPhone 6 này lên ios 11 được không?",
      "answer": "Chào bạn, Điện thoại này lên được hệ điều hành iOS 11 nhưng mình khuyên bạn không nên lên vì máy chạy khá chậm bạn nhé. Thông tin đến bạn .",
      "relate_q_q": -1
    },
    {
      "score": 16.166704,
      "id": "21789689",
      "field_search": "question",
      "question": "cho hỏi lumia 1520 đổi được ip6 32GB không, nếu được thì bù bao nhiêu vậy",
      "answer": "Chào anh, Rất tiếc hiện tại sản phẩm Lumia 1520 đã ra mắt khá lâu rồi nên không còn được hỗ trợ đổi trả anh nhé. Mong anh thông cảm. Thông tin đến anh!",
      "relate_q_q": -1
    },
    {
      "score": 16.161398,
      "id": "19976220",
      "field_search": "question",
      "question": "Cho mh hỏi bản 32gb có mấy mầu ạ",
      "answer": "Chào anh Hiện sản phẩm mà anh quan tâm chỉ có 1 màu vàng đồng thôi anh nhé. Mong anh thông cảm và tham khảo màu sản phẩm trên giúp em được không ạ? Xin gửi thông tin đến anh ",
      "relate_q_q": -1
    },
    {
      "score": 16.130442,
      "id": "25381398",
      "field_search": "question",
      "question": "Ad cho mình hỏi: mình đag dùng ip 6 32g 2017 và đang dùng ios 11.2.5. Mình muốn hạ xuống ios 10 thì có được không ạ?",
      "answer": "Chào chị Dạ. Hệ điều hành nâng lên rồi thì không hạ xuống được ạ. Thông tin đến chị !",
      "relate_q_q": -1
    },
    {
      "score": 16.125784,
      "id": "25098055",
      "field_search": "question",
      "question": "Cho e hỏi ip6 có nên cập nhật bản ios 11.2.5 k? Bản mới có khắc phục hao pin k",
      "answer": "Chào bạn, Nếu bạn đang dùng hệ điều hành iOS 11 thì cứ cập nhật lên để dùng tốt nhất và bản mới mình thấy không làm máy giật lag hơn và cũng không gây hao PIN hơn các bản iOS 11 trước đó bạn nhé. Nếu đang dùng iOS 10 thì không nên lên nhé bạn .Thông tin đến bạn .",
      "relate_q_q": -1
    },
    {
      "score": 16.103703,
      "id": "19510923",
      "field_search": "question",
      "question": "Ad cho e hỏi ip 6 32g hiện tại đag sài ios 10.3.1 có nên cập nhật lên nửa k nếu cập nhật thì ios mấy là phù hợp nhất",
      "answer": "Chào bạn, Nếu bạn thấy máy chưa ổn định thì bạn  có thể cập nhật lên ios 10.3.2, bản cập nhật của hãng nên an toàn bạn nhé! Thân chào bạn!",
      "relate_q_q": -1
    },
    {
      "score": 16.095068,
      "id": "22021550",
      "field_search": "question",
      "question": "Hạ xuống ios 9 thi làm thế nào vậy",
      "answer": "Chào bạn,Rất tiếc không thể hạ xuống IOS 9 khi đã cập nhật IOS cao hơn bạn nhé.Thân chào bạn !",
      "relate_q_q": -1
    },
    {
      "score": 16.092031,
      "id": "21360432",
      "field_search": "question",
      "question": "Cho mình hỏi mình ma nâng cấp lên ios 11 beta 8 bây giờ mún xún ios 10 thì phải làm sao ạ Xún trực tiếp lun hay là phải xún ios 11 beta 7,6,5... rồi ms xún đc ạ Làm như vậy có bị treo cáp ko e thấy trên mạng nó đồn dưz lẵm",
      "answer": "Chào bạn, Bạn có thể hạ từ hệ điều hành iOS 11 xuống IOS 10.3.3 theo hướng dẫn tại .Xuống trực tiếp luôn bạn nhé. Thông tin đến bạn .",
      "relate_q_q": -1
    },
    {
      "score": 16.085567,
      "id": "25589151",
      "field_search": "question",
      "question": "Cho hỏi là khi mua về thì Máy chạy ios nhiêu, và nếu resert máy thì có quay lại đc ios ban đầu hay không? Mình đang sài ip6 ios 11.2.6 và có hiện tượng đơ nhẹ khi sử dụng",
      "answer": "Chào bạn,Máy mua về sẽ chạy IOS11 và việc reset không làm thay đổi phiên bản hệ điều hành, về việc máy chạy không mượt bạn vui lòng nhấn giữ phím nguồn và home cho đến khi máy tắt và khởi động máy lại giúp mình bạn nhé.Xin thông tin đến bạn.",
      "relate_q_q": 1
    },
    {
      "score": 15.921021,
      "id": "27466180",
      "field_search": "question",
      "question": "Qtv cho mình hỏi với Máy này Trả trước 0 đồng góp trong 12 tháng được không qtv?. Nếu được thì mỗi tháng mất bao tiền vậy qtv?",
      "answer": "Chào chị,Trường hợp này thì vẫn được chị nha. Nhưng với điều kiện của gói trả góp thì chị cần đủ tuổi từ 20 đến 60 tính cả tháng lẫn ngày. Có các giấy tờ như CMND (không quá 15 năm kể từ ngày cấp và thấy rõ hình, chữ), hộ khẩu (có tên trong hộ khẩu) và hóa đơn điện đó ạ. Nếu ưng ý thì chị có thể cho em thông tin về độ tuổi của anh, số giấy tờ chị hiện có để bên em có thể tư vấn cho chị một gói trả góp phù hợp chị nhé. Mong phản hồi từ chị!",
      "relate_q_q": -1
    },
    {
      "score": 15.919117,
      "id": "20045804",
      "field_search": "question",
      "question": "Cho mình hỏi là máy mình nhở nâng cấp lên ios 11 giờ mình muốn quay về ios 10 có được không.",
      "answer": "Chào bạn, Rất tiếc là hãng chỉ hỗ trợ người dùng nâng cấp hệ điều hành lên, chứ không hỗ trợ hạ xuống bạn nhé  Thân chào bạn!",
      "relate_q_q": -1
    },
    {
      "score": 15.909977,
      "id": "25498360",
      "field_search": "question",
      "question": "Máy này lên ios 11.2.6 được ko vậy ad",
      "answer": "Chào bạn, Theo mình thấy thì điện thoại này được hỗ trợ cập nhật lên ios 11.2.6 bạn nhé Thân chào bạn!",
      "relate_q_q": -1
    },
    {
      "score": 15.885815,
      "id": "27526064",
      "field_search": "question",
      "question": "Iphone 6 phiên bản Mới . Mua đã có ios 11.2 rồi. Ad cho hỏi có ảnh hưởng gì ko",
      "answer": "Chào anh,Em thấy phiên bản mới iphone 6 sử dụng hoàn toàn bình thường máy vẫn chạy mượt nên anh yên tâm về vấn đề này nha.Thông tin đến anh.",
      "relate_q_q": -1
    },
    {
      "score": 15.882825,
      "id": "26441519",
      "field_search": "question",
      "question": "Shop có hổ trợ cài iOS 10.3.3 cho dòng máy này không ạ",
      "answer": "Chào bạn,Bên mình không hỗ trợ hạ cấp phần mềm cho máy này bạn nha.Chia sẻ cùng bạn !",
      "relate_q_q": -1
    },
    {
      "score": 15.834394,
      "id": "21846693",
      "field_search": "question",
      "question": "Nếu mua con này ngoài thế giới di động thì đã lên ios 11 chua",
      "answer": "Chào anh,Dạ chưa ạ, khi mua sản phẩm trên tại siêu thị thì máy chỉ ở IOS 10 thôi nha.Thông tin đến anh.",
      "relate_q_q": -1
    },
    {
      "score": 15.823856,
      "id": "18625846",
      "field_search": "question",
      "question": "cho hoi s khi mua hạ xuốg ios 9 dx k",
      "answer": "Chào anh,Hiện tại anh không thể hạ xuống ios 9 vì apple đã khoá các bản ios thấp hơn rồi ạ.Thông tin đến anh.",
      "relate_q_q": -1
    },
    {
      "score": 15.816585,
      "id": "25993365",
      "field_search": "question",
      "question": "cho mình hỏi Điện thoại iPhone 6 32GB la bản quốc tế hay bản lock vậy bạn",
      "answer": "Chào bạn, xin lỗi đã để bạn đợi lâu nhé Điện thoại này bên mình kinh doanh là bản quốc tế bạn nhé Thân chào bạn!",
      "relate_q_q": -1
    },
    {
      "score": 15.784606,
      "id": "21345986",
      "field_search": "question",
      "question": "Qtv ơi cho em hỏi ip6 của em mới mua về mà không có sạc 8 tiếng lần đầu thì có bị gì không vậy Qtv?",
      "answer": "Chào anh,Khi mua máy iPhone về thì anh không cần sạc trong 8 tiếng đâu ạ và không bị gì đâu anh nhé. Khi nào gần hết Pin anh chỉ cần sạc đầy là sử dụng bình thường anh nhaThông tin đến anh !",
      "relate_q_q": -1
    },
    {
      "score": 15.778036,
      "id": "26006007",
      "field_search": "question",
      "question": "Cho tui hỏi là iphone 6 này là bản quốc tế hay bản lock vậy",
      "answer": "Chào bạn,Máy bên mình kinh doanh là bản quốc tế bạn nhé.Thông tin đến bạn !",
      "relate_q_q": -1
    },
    {
      "score": 15.760645,
      "id": "28264128",
      "field_search": "question",
      "question": "Cho mình hỏi, iphone này là bản iphone word hay lock vậy",
      "answer": "Chào bạn,Iphone bên mình kinh doanh là bản quốc tế bạn nhé.Thông tin đến bạn !",
      "relate_q_q": -1
    },
    {
      "score": 15.752396,
      "id": "24975026",
      "field_search": "question",
      "question": "tại sao anh mua máy iphone 6 mới. thông số trên web ghi ios 10 mà về anh coi lại thì lại là ios 11.1??",
      "answer": "Chào bạn, xin lỗi đã để bạn đợi lâu nhé Theo mình thấy thì những lô hàng mới sẽ được Apple cập nhật lên ios 11 mới bạn nhé Thân chào bạn!",
      "relate_q_q": -1
    },
    {
      "score": 15.722254,
      "id": "21360172",
      "field_search": "question",
      "question": "Cho mình hỏi mình ma nâng cấp lên ios 11 beta 8 bây giờ mún xún ios 10 thì phải làm sao ạ Xún trực tiếp lun hay là phải xún ios 11 beta 7,6,5... rồi ms xún đc ạ Làm như vậy có bị treo cáp ko e thấy trên mạng nó đồn dưz lẵm",
      "answer": "Chào bạn,Nếu bạn đã nâng cấp iOS 11 thì có thể tham khảo  để hạ cấp cho máy nhé, và thông thường nếu bạn thao tác đúng thì máy sẽ không bị lỗi treo cáp nha.Thông tin đến bạn!",
      "relate_q_q": -1
    },
    {
      "score": 15.667992,
      "id": "27477861",
      "field_search": "question",
      "question": "Ios 11 có hạ về 10 đc kg qtv",
      "answer": "Chào bạn,Rất tiếc, hiện tại apple không hỗ trợ hạ cấp về iOS 10 nữa bạn nhé. Xin thông tin đến bạn ạ !",
      "relate_q_q": -1
    },
    {
      "score": 15.664551,
      "id": "23727906",
      "field_search": "question",
      "question": "Cho mình hỏi tí . Mình muốn chuyển từ ios 11.0.2 ve ios 10 dược không ạ ?",
      "answer": "Chào bạn,Dạ hiện tại không thể quay về IOS 10 nữa do Apple đã khóa bản này rồi ạ.Xin thông tin đến bạn.",
      "relate_q_q": -1
    },
    {
      "score": 15.614001,
      "id": "24027726",
      "field_search": "question",
      "question": "em dang 6 32gb chay IOS 11.2 muon ha xuong IOS 10 phai lm s anh",
      "answer": "Chào bạn, Rất tiếc Apple không còn cho phép hạ xuống hệ điều hành iOS 10 nữa nên không hạ được bạn nhé. Thông tin đến bạn .",
      "relate_q_q": -1
    },
    {
      "score": 15.600973,
      "id": "25327745",
      "field_search": "question",
      "question": "Cho mình hỏi iphone 6 plus có bản cập nhật  ios 11.3 không vậy ạ?",
      "answer": "Chào bạn,Điện thoại iPhone 6 Plus chưa có bản cập nhật IOS 11.3 chính thức bạn nhé.Thân chào bạn !",
      "relate_q_q": -1
    },
    {
      "score": 15.586561,
      "id": "22499607",
      "field_search": "question",
      "question": "Qtv mình đang sài con 6s  mình mới nhận đc bản cập nhật ios 11.0.3 vây cho mình hỏi có lên cập nhật lên ko a. Nếu cập nhật lên thì máy có bị làm sao ko ạ",
      "answer": "Chào bạn Trường hợp này theo 1 số phản hồi của người sử dụng khi cập nhật lên có hao Pin hơn , vì vậy bạn có thể cân nhắc trước khi cập nhật bạn nhé .Thông tin đến bạn .",
      "relate_q_q": -1
    },
    {
      "score": 15.566292,
      "id": "18636005",
      "field_search": "question",
      "question": "Cho e hỏi e mới mua máy này được 3 hôm , phần cài đặt gửi thông báo về là cài đặt ios10.3 sẽ giúp cài đặt iphone của bạn hoàn thiện hơn , e nhấn vào cài đặt , có nghĩ là luk đầu là ios10 , vậy e nâng cấp ios lên chắc không ảnh hưởng j đâu ad nỉ",
      "answer": "Chào bạn, Điện thoại này chạy hệ điều hành IOS 10.3.1 hoàn toàn mượt mà và ổn định nên bạn có thể nâng cấp lên được bạn nhé .Thân chào bạn !",
      "relate_q_q": -1
    }
  ]
}